yadage/__init__.py
yadage/controllers.py
yadage/creators.py
yadage/interactive.py
yadage/logutils.py
yadage/manualcli.py
yadage/manualutils.py
yadage/reset.py
yadage/serialize.py
yadage/stages.py
yadage/steering.py
yadage/steering_api.py
yadage/steering_object.py
yadage/strategies.py
yadage/tasks.py
yadage/utilcli.py
yadage/utils.py
yadage/visualize.py
yadage/wflow.py
yadage/wflownode.py
yadage/wflowstate.py
yadage/wflowview.py
yadage/workflow_loader.py
yadage/backends/__init__.py
yadage/backends/caching.py
yadage/backends/federatedbackend.py
yadage/backends/packtivitybackend.py
yadage/backends/trivialbackend.py
yadage/handlers/__init__.py
yadage/handlers/expression_handlers.py
yadage/handlers/predicate_handlers.py
yadage/handlers/scheduler_handlers.py
yadage/handlers/utils.py
yadage/state_providers/__init__.py
yadage/state_providers/localposix.py
yadage-0.21.0.dist-info/LICENSE
yadage-0.21.0.dist-info/METADATA
yadage-0.21.0.dist-info/WHEEL
yadage-0.21.0.dist-info/entry_points.txt
yadage-0.21.0.dist-info/top_level.txt
yadage-0.21.0.dist-info/RECORD
