Metadata-Version: 2.1
Name: yadage
Version: 0.21.0
Summary: yadage - YAML based adage
Home-page: https://github.com/yadage/yadage
Author: Lukas Heinrich
Author-email: lukas.heinrich@cern.ch
License: MIT
Project-URL: Documentation, https://github.com/yadage/yadage
Project-URL: Source Code, https://github.com/yadage/yadage
Project-URL: Issue Tracker, https://github.com/yadage/yadage/issues
Keywords: physics yadage
Classifier: Development Status :: 4 - Beta
Classifier: License :: OSI Approved :: MIT License
Classifier: Intended Audience :: Science/Research
Classifier: Topic :: Scientific/Engineering
Classifier: Topic :: Scientific/Engineering :: Physics
Classifier: Programming Language :: Python :: 3
Classifier: Programming Language :: Python :: 3 :: Only
Classifier: Programming Language :: Python :: 3.8
Classifier: Programming Language :: Python :: 3.9
Classifier: Programming Language :: Python :: 3.10
Classifier: Programming Language :: Python :: 3.11
Classifier: Programming Language :: Python :: Implementation :: CPython
Classifier: Operating System :: OS Independent
Requires-Python: >=3.8
License-File: LICENSE
Requires-Dist: adage >=0.10.2
Requires-Dist: packtivity >=0.16.2
Requires-Dist: yadage-schemas >=0.10.0
Requires-Dist: click >=7.0
Requires-Dist: psutil
Requires-Dist: requests[security] >=2.9
Requires-Dist: pyyaml
Requires-Dist: jsonref
Requires-Dist: jsonschema
Requires-Dist: jsonpointer >=1.10
Requires-Dist: jsonpath-rw
Requires-Dist: checksumdir
Requires-Dist: glob2
Requires-Dist: jq
Provides-Extra: all
Requires-Dist: adage[viz] >=0.10.3 ; extra == 'all'
Requires-Dist: black[jupyter] >=22.1.0 ; extra == 'all'
Requires-Dist: celery ; extra == 'all'
Requires-Dist: isort ; extra == 'all'
Requires-Dist: pre-commit ; extra == 'all'
Requires-Dist: pydotplus >=2.0.0 ; extra == 'all'
Requires-Dist: pyflakes ; extra == 'all'
Requires-Dist: pytest-cov >=2.5.1 ; extra == 'all'
Requires-Dist: pytest >=6.0.0 ; extra == 'all'
Requires-Dist: redis ; extra == 'all'
Provides-Extra: celery
Requires-Dist: celery ; extra == 'celery'
Requires-Dist: redis ; extra == 'celery'
Provides-Extra: develop
Requires-Dist: adage[viz] >=0.10.3 ; extra == 'develop'
Requires-Dist: pydotplus >=2.0.0 ; extra == 'develop'
Requires-Dist: pre-commit ; extra == 'develop'
Requires-Dist: pytest >=6.0.0 ; extra == 'develop'
Requires-Dist: pytest-cov >=2.5.1 ; extra == 'develop'
Provides-Extra: lint
Requires-Dist: pyflakes ; extra == 'lint'
Requires-Dist: isort ; extra == 'lint'
Requires-Dist: black[jupyter] >=22.1.0 ; extra == 'lint'
Provides-Extra: viz
Requires-Dist: adage[viz] >=0.10.3 ; extra == 'viz'
Requires-Dist: pydotplus >=2.0.0 ; extra == 'viz'
